MANIFEST.in
README.rst
setup.py
collective/.DS_Store
collective/__init__.py
collective/__init__.pyc
collective.ptg.sheetgallery.egg-info/PKG-INFO
collective.ptg.sheetgallery.egg-info/SOURCES.txt
collective.ptg.sheetgallery.egg-info/dependency_links.txt
collective.ptg.sheetgallery.egg-info/entry_points.txt
collective.ptg.sheetgallery.egg-info/namespace_packages.txt
collective.ptg.sheetgallery.egg-info/not-zip-safe
collective.ptg.sheetgallery.egg-info/requires.txt
collective.ptg.sheetgallery.egg-info/top_level.txt
collective/ptg/.DS_Store
collective/ptg/__init__.py
collective/ptg/__init__.pyc
collective/ptg/sheetgallery/.DS_Store
collective/ptg/sheetgallery/__init__.py
collective/ptg/sheetgallery/__init__.pyc
collective/ptg/sheetgallery/configure.zcml
collective/ptg/sheetgallery/i18n.sh
collective/ptg/sheetgallery/sheetgallery.pt
collective/ptg/sheetgallery/locales/.DS_Store
collective/ptg/sheetgallery/locales/collective.ptg.sheetgallery.pot
collective/ptg/sheetgallery/locales/en/.DS_Store
collective/ptg/sheetgallery/locales/en/LC_MESSAGES/collective.ptg.sheetgallery.mo
collective/ptg/sheetgallery/locales/en/LC_MESSAGES/collective.ptg.sheetgallery.po
collective/ptg/sheetgallery/locales/no/.DS_Store
collective/ptg/sheetgallery/locales/no/LC_MESSAGES/collective.ptg.sheetgallery.mo
collective/ptg/sheetgallery/locales/no/LC_MESSAGES/collective.ptg.sheetgallery.po
collective/ptg/sheetgallery/resources/.DS_Store
collective/ptg/sheetgallery/resources/1354108158_package_utilitie.png
collective/ptg/sheetgallery/resources/1354108195_exit.png
collective/ptg/sheetgallery/resources/1354108233_gear.png
collective/ptg/sheetgallery/resources/1354108258_fonts.png
collective/ptg/sheetgallery/resources/1354108318_font.png
collective/ptg/sheetgallery/resources/download_share.png
collective/ptg/sheetgallery/resources/downloadimage.jpg
collective/ptg/sheetgallery/resources/no_style.css
collective/ptg/sheetgallery/resources/style.css
docs/HISTORY.txt
docs/INSTALL.txt
docs/LICENSE.GPL
docs/LICENSE.txt